{
    "generatedAt":  "2026-07-21T08:12:40+09:00",
    "cutoffAt":  "2026-07-20T08:11:30+09:00",
    "articleCount":  79,
    "articles":  [
                     {
                         "source":  "NHK 経済",
                         "title":  "生産地 備蓄米の早期買い戻し求める声強まる 政府は慎重に検討",
                         "url":  "https://news.web.nhk/newsweb/na/na-k10015181311000",
                         "description":  "コメ価格の値下がりを受けて、生産地からは、新米が本格的に出回る前に備蓄米の買い戻しを行い、価格を下支えするよう政府に求める声が強まっています。一方で政府内には、物価の上昇が続く中でコメが値上がりするこ…",
                         "publishedAt":  "2026-07-21T06:59:44+09:00",
                         "fetchedAt":  "2026-07-21T08:11:39+09:00"
                     },
                     {
                         "source":  "NHK 経済",
                         "title":  "トヨタ 近健太社長 “開発や生産の効率化進め 稼ぐ力強化を”",
                         "url":  "https://news.web.nhk/newsweb/na/na-k10015181321000",
                         "description":  "トヨタ自動車の近健太社長は、報道各社のインタビューに応じ、新興メーカーを含めて競争が激しくなる中、部品の種類の削減などで開発や生産の効率化を進め、会社の稼ぐ力を一段と強化する考えを示しました。",
                         "publishedAt":  "2026-07-21T06:45:42+09:00",
                         "fetchedAt":  "2026-07-21T08:11:39+09:00"
                     },
                     {
                         "source":  "Yahoo!ニュース 経済",
                         "title":  "日米合意1年 関税の負担依然重く",
                         "url":  "https://news.yahoo.co.jp/pickup/6588606?source=rss",
                         "description":  "",
                         "publishedAt":  "2026-07-20T10:54:28+09:00",
                         "fetchedAt":  "2026-07-21T08:11:42+09:00"
                     },
                     {
                         "source":  "Yahoo!ニュース 経済",
                         "title":  "マンジャロの違法転売 取り巻く闇",
                         "url":  "https://news.yahoo.co.jp/pickup/6588598?source=rss",
                         "description":  "",
                         "publishedAt":  "2026-07-20T09:32:41+09:00",
                         "fetchedAt":  "2026-07-21T08:11:42+09:00"
                     },
                     {
                         "source":  "Yahoo!ニュース 経済",
                         "title":  "契約書や許可なし ヤミ小作の実態",
                         "url":  "https://news.yahoo.co.jp/pickup/6588600?source=rss",
                         "description":  "",
                         "publishedAt":  "2026-07-20T09:49:28+09:00",
                         "fetchedAt":  "2026-07-21T08:11:42+09:00"
                     },
                     {
                         "source":  "Yahoo!ニュース 経済",
                         "title":  "今年の夏はウナギが値下がり なぜ",
                         "url":  "https://news.yahoo.co.jp/pickup/6588621?source=rss",
                         "description":  "",
                         "publishedAt":  "2026-07-20T13:10:20+09:00",
                         "fetchedAt":  "2026-07-21T08:11:42+09:00"
                     },
                     {
                         "source":  "Yahoo!ニュース 経済",
                         "title":  "運営もう無理 酷暑で海水浴離れ",
                         "url":  "https://news.yahoo.co.jp/pickup/6588617?source=rss",
                         "description":  "",
                         "publishedAt":  "2026-07-20T12:30:38+09:00",
                         "fetchedAt":  "2026-07-21T08:11:42+09:00"
                     },
                     {
                         "source":  "Yahoo!ニュース 経済",
                         "title":  "ローソン「車中泊」50代利用者も",
                         "url":  "https://news.yahoo.co.jp/pickup/6588655?source=rss",
                         "description":  "",
                         "publishedAt":  "2026-07-20T18:30:22+09:00",
                         "fetchedAt":  "2026-07-21T08:11:42+09:00"
                     },
                     {
                         "source":  "ITmedia ビジネス",
                         "title":  "売上の3割を捨てた「下請け町工場」 自社ブランドのコーヒーフィルターが世界80の国・地域で求められる理由",
                         "url":  "https://www.itmedia.co.jp/business/articles/2607/21/news026.html",
                         "description":  "売上の3割を失う覚悟で、OEM中心の事業から自社ブランドへと舵を切った大分県の町工場。社長自らが世界を飛び回り、コーヒーフィルターを世界80の国・地域へ広げた。下請けから脱し、海外でブランドを育てた方法とは。",
                         "publishedAt":  "2026-07-21T07:30:00+09:00",
                         "fetchedAt":  "2026-07-21T08:11:44+09:00"
                     },
                     {
                         "source":  "ITmedia ビジネス",
                         "title":  "「教育の学研」過去最高売上でも株価は半減、なぜ？ 売上の半分を占める「介護ビジネス」の課題",
                         "url":  "https://www.itmedia.co.jp/business/articles/2607/21/news018.html",
                         "description":  "「教育の学研」というイメージが強い学研HDだが、現在は医療福祉事業が売上高の約半分を占める。5期連続増収で売上高は過去最高を更新する一方、株価はピーク時から半減。なぜ業績好調でも市場から評価されないのか。事業構造の変化と今後の課題を読み解く。",
                         "publishedAt":  "2026-07-21T07:30:00+09:00",
                         "fetchedAt":  "2026-07-21T08:11:44+09:00"
                     },
                     {
                         "source":  "ITmedia ビジネス",
                         "title":  "NTT、ソフトバンク、サカナAI――国産AI開発「成功組」の“ある共通点”",
                         "url":  "https://www.itmedia.co.jp/business/articles/2607/21/news036.html",
                         "description":  "NTTやソフトバンク、サカナAIなどの「AI開発に成功した企業」には“ある共通点”がある。彼らはどのような技術を活用し、AI開発を成し遂げたのか。",
                         "publishedAt":  "2026-07-21T07:00:00+09:00",
                         "fetchedAt":  "2026-07-21T08:11:44+09:00"
                     },
                     {
                         "source":  "ITmedia ビジネス",
                         "title":  "「耳をふさがない集音器」にNTTやカシオが参入 補聴器普及率15.6％の日本で広がる新市場",
                         "url":  "https://www.itmedia.co.jp/business/articles/2607/21/news005.html",
                         "description":  "耳をふさがない「集音器」市場が活況だ。NTTソノリティやカシオ計算機、ミライスピーカーなどが同領域の新製品を発売し、次々ヒット。クラウドファンディングで約4.5億円を集める事例も出ている。なぜ同市場が盛り上がっているのか取材したところ……。",
                         "publishedAt":  "2026-07-21T07:00:00+09:00",
                         "fetchedAt":  "2026-07-21T08:11:44+09:00"
                     },
                     {
                         "source":  "ITmedia ビジネス",
                         "title":  "「給料、自分で決めていいよ」 組織図も稟議もない老舗石鹸メーカーが、管理ナシで成果を出せる理由",
                         "url":  "https://www.itmedia.co.jp/business/articles/2607/21/news020.html",
                         "description":  "社員が自ら希望する給与額を会社に提示する――。そんな「自己申告型給与制度」を導入する老舗メーカーがある。組織図も職種定義書もなく、それでも高い生産性を維持する木村石鹸工業の組織づくりから、人事評価の新たなヒントを探る。",
                         "publishedAt":  "2026-07-21T07:00:00+09:00",
                         "fetchedAt":  "2026-07-21T08:11:44+09:00"
                     },
                     {
                         "source":  "ITmedia ビジネス",
                         "title":  "Googleが指南する、AI検索を味方にする「10のヒント」 オープンハウスでは「コンバージョン数63％増」の事例も",
                         "url":  "https://www.itmedia.co.jp/business/articles/2607/21/news014.html",
                         "description":  "AIの回答だけで満足してそのまま離脱してしまう、いわゆる“ゼロクリック問題”が深刻化している。マーケターは今「AI対策」に躍起になっているが、その取り組みは本当に意味を成しているのだろうか。",
                         "publishedAt":  "2026-07-21T06:00:00+09:00",
                         "fetchedAt":  "2026-07-21T08:11:44+09:00"
                     },
                     {
                         "source":  "ITmedia ビジネス",
                         "title":  "セミセルフレジが増えても、なぜか人件費は減らない？ 設備投資を空回りさせる「シフトの落とし穴」",
                         "url":  "https://www.itmedia.co.jp/business/articles/2607/21/news006.html",
                         "description":  "セミセルフレジは友人レジと比較して作業効率は「1.5倍超」向上するとされています。しかし、実際の店舗運営でレジ人時生産性の削減効果が実際の数字よりも低くなるケースが多く見られます。なぜでしょうか？",
                         "publishedAt":  "2026-07-21T06:00:00+09:00",
                         "fetchedAt":  "2026-07-21T08:11:44+09:00"
                     },
                     {
                         "source":  "ITmedia ビジネス",
                         "title":  "企業の5割、「猛暑・酷暑」で業務に支障 最も多かった対策は？",
                         "url":  "https://www.itmedia.co.jp/business/articles/2607/21/news040.html",
                         "description":  "帝国データバンクの調査で、猛暑日や酷暑日に業務や事業活動へ支障が出た企業は50.0％に上った。企業の約9割が猛暑対策を実施しており、最も多かった対策は何だったのか。",
                         "publishedAt":  "2026-07-21T05:30:00+09:00",
                         "fetchedAt":  "2026-07-21T08:11:44+09:00"
                     },
                     {
                         "source":  "ITmedia ビジネス",
                         "title":  "なぜ象印は「象」をマークに選んだのか タイガーとの競争とブランド戦略",
                         "url":  "https://www.itmedia.co.jp/business/articles/2607/20/news001.html",
                         "description":  "象印はなぜ「象」をブランドマークに選んだのか。その背景には、競合タイガーとの市場競争と、家族的で温かい象のイメージを重ねた戦略があった。大阪の魔法瓶産業の中で育まれたブランド形成の歴史をひもとく。",
                         "publishedAt":  "2026-07-20T09:00:00+09:00",
                         "fetchedAt":  "2026-07-21T08:11:44+09:00"
                     },
                     {
                         "source":  "朝日新聞 経済",
                         "title":  "金利上昇の本質とは 河野龍太郎氏の語る「時代の変化」と日本の幻想",
                         "url":  "https://www.asahi.com/articles/ASV7J1R23V7JULFA01QM.html?ref=rss",
                         "description":  "",
                         "publishedAt":  "",
                         "fetchedAt":  "2026-07-21T08:11:45+09:00"
                     },
                     {
                         "source":  "朝日新聞 経済",
                         "title":  "【まとめてわかる】政権が重視する「骨太の方針」って何のこと？",
                         "url":  "https://www.asahi.com/articles/ASV7K2SLDV7KULFA02HM.html?ref=rss",
                         "description":  "",
                         "publishedAt":  "",
                         "fetchedAt":  "2026-07-21T08:11:45+09:00"
                     },
                     {
                         "source":  "朝日新聞 経済",
                         "title":  "トヨタ社長「国内生産や供給網の水準を維持」 トランプ関税でも堅調",
                         "url":  "https://www.asahi.com/articles/ASV7L46THV7LULFA006M.html?ref=rss",
                         "description":  "",
                         "publishedAt":  "",
                         "fetchedAt":  "2026-07-21T08:11:45+09:00"
                     },
                     {
                         "source":  "朝日新聞 経済",
                         "title":  "EU、中国系ネット通販「アリエク」に制裁金 過去最高1022億円",
                         "url":  "https://www.asahi.com/articles/ASV7N35KMV7NUHBI002M.html?ref=rss",
                         "description":  "",
                         "publishedAt":  "",
                         "fetchedAt":  "2026-07-21T08:11:45+09:00"
                     },
                     {
                         "source":  "朝日新聞 経済",
                         "title":  "商船三井の安全管理トップ、ホルムズ海峡通過「安全への確証で判断」",
                         "url":  "https://www.asahi.com/articles/ASV7N2JX6V7NULFA002M.html?ref=rss",
                         "description":  "",
                         "publishedAt":  "",
                         "fetchedAt":  "2026-07-21T08:11:45+09:00"
                     },
                     {
                         "source":  "朝日新聞 経済",
                         "title":  "現役教員がビール会社を起業 めざすは「ビジネスを通じて教育を」",
                         "url":  "https://www.asahi.com/articles/ASV7H25FCV7HULFA00LM.html?ref=rss",
                         "description":  "",
                         "publishedAt":  "",
                         "fetchedAt":  "2026-07-21T08:11:45+09:00"
                     },
                     {
                         "source":  "朝日新聞 経済",
                         "title":  "観光客急増で深刻化するごみ問題 京都嵐山発の地域協働モデルとは",
                         "url":  "https://www.asahi.com/articles/ASV7J1QLFV7JOXIE00BM.html?ref=rss",
                         "description":  "",
                         "publishedAt":  "",
                         "fetchedAt":  "2026-07-21T08:11:45+09:00"
                     },
                     {
                         "source":  "朝日新聞 経済",
                         "title":  "トンネル工事で枯れた水 リニアが問われる環境への責任と期待の両立",
                         "url":  "https://www.asahi.com/articles/ASV7J10ZWV7JOIPE00KM.html?ref=rss",
                         "description":  "",
                         "publishedAt":  "",
                         "fetchedAt":  "2026-07-21T08:11:45+09:00"
                     },
                     {
                         "source":  "朝日新聞 経済",
                         "title":  "仕事と育児、両立阻む「18歳の壁」 離職の危機を救う制度とは？",
                         "url":  "https://www.asahi.com/articles/ASV7K2CHDV7KULFA01DM.html?ref=rss",
                         "description":  "",
                         "publishedAt":  "",
                         "fetchedAt":  "2026-07-21T08:11:45+09:00"
                     },
                     {
                         "source":  "朝日新聞 経済",
                         "title":  "全東信は「昭和のなごり」 専門家が指摘するカード会社の責任とは",
                         "url":  "https://www.asahi.com/articles/ASV7K3Q3LV7KPLFA00FM.html?ref=rss",
                         "description":  "",
                         "publishedAt":  "",
                         "fetchedAt":  "2026-07-21T08:11:45+09:00"
                     },
                     {
                         "source":  "朝日新聞 経済",
                         "title":  "「全東信が生き残っていたとは」 専門家も驚くカード会社の対応",
                         "url":  "https://www.asahi.com/articles/ASV7K3S9BV7KPLFA00FM.html?ref=rss",
                         "description":  "",
                         "publishedAt":  "",
                         "fetchedAt":  "2026-07-21T08:11:45+09:00"
                     },
                     {
                         "source":  "朝日新聞 経済",
                         "title":  "「サービス終了」と電話説明でうそ 光回線サービスの勧誘に要注意",
                         "url":  "https://www.asahi.com/articles/ASV722DFJV72UTFL00QM.html?ref=rss",
                         "description":  "",
                         "publishedAt":  "",
                         "fetchedAt":  "2026-07-21T08:11:45+09:00"
                     },
                     {
                         "source":  "朝日新聞 経済",
                         "title":  "ライバル旅館同士が宿泊データを共有 城崎温泉が挑む地域活性化策",
                         "url":  "https://www.asahi.com/articles/ASV7J1HB0V7JOXIE01FM.html?ref=rss",
                         "description":  "",
                         "publishedAt":  "",
                         "fetchedAt":  "2026-07-21T08:11:45+09:00"
                     },
                     {
                         "source":  "朝日新聞 経済",
                         "title":  "国産のヒト型ロボットに「勝ち筋」はあるか 米中が席巻する現在地",
                         "url":  "https://www.asahi.com/articles/ASV7K05S2V7KPLFA002M.html?ref=rss",
                         "description":  "",
                         "publishedAt":  "",
                         "fetchedAt":  "2026-07-21T08:11:45+09:00"
                     },
                     {
                         "source":  "朝日新聞 経済",
                         "title":  "観光地での「二重価格」、どんな制度？ インドでは22倍の入場料も",
                         "url":  "https://www.asahi.com/articles/ASV7H2W6CV7HUHBI011M.html?ref=rss",
                         "description":  "",
                         "publishedAt":  "",
                         "fetchedAt":  "2026-07-21T08:11:45+09:00"
                     },
                     {
                         "source":  "朝日新聞 経済",
                         "title":  "迷走したリニアの9年間 知事は「恥を知れ」と名指しで国の局長批判",
                         "url":  "https://www.asahi.com/articles/ASV7H2RGLV7HUTIL00KM.html?ref=rss",
                         "description":  "",
                         "publishedAt":  "",
                         "fetchedAt":  "2026-07-21T08:11:45+09:00"
                     },
                     {
                         "source":  "朝日新聞 経済",
                         "title":  "住宅ローンのこと聞いたのに「保険見直しを」 FP相談の注意点は？",
                         "url":  "https://www.asahi.com/articles/ASV7H1VZLV7HULFA01XM.html?ref=rss",
                         "description":  "",
                         "publishedAt":  "",
                         "fetchedAt":  "2026-07-21T08:11:45+09:00"
                     },
                     {
                         "source":  "東洋経済オンライン",
                         "title":  "｢洗濯物がリビングに散乱｣悲惨な自宅を救った\"超身近な便利グッズ\"…漫画『私だけが頑張る片付けはもうごめんだ』第4話 | ライフ | 東洋経済オンライン",
                         "url":  "https://toyokeizai.net/articles/-/950683?utm_source=rss\u0026utm_medium=http\u0026utm_campaign=link_back",
                         "description":  "目指すは（映えなくてもいいから） 家族全員ができる片付けーー。子ども4人＋犬猫で毎日カオス！片付けても5分で床がジャングル化……原因は、“子供に無理なやり方”でした。子どもの動きに合わせて片付けの仕…",
                         "publishedAt":  "2026-07-21T08:00:00+09:00",
                         "fetchedAt":  "2026-07-21T08:11:46+09:00"
                     },
                     {
                         "source":  "東洋経済オンライン",
                         "title":  "50代女性の半数が経験｢指の痛み･腫れ･変形｣は\"年齢のせい\"だけではなかった ｢ヘバーデン結節｣のセルフケアと治療法 | ライフ | 東洋経済オンライン",
                         "url":  "https://toyokeizai.net/articles/-/951358?utm_source=rss\u0026utm_medium=http\u0026utm_campaign=link_back",
                         "description":  "指の関節が腫れる･こわばる､ペットボトルのフタが開けられない……。40代後半から50代にかけて急増する手指の不調。｢年齢のせい｣とあきらめていませんか。ヘバーデン結節をはじめとする指の疾患の原因と､…",
                         "publishedAt":  "2026-07-21T07:30:00+09:00",
                         "fetchedAt":  "2026-07-21T08:11:46+09:00"
                     },
                     {
                         "source":  "東洋経済オンライン",
                         "title":  "｢日本のルールは守らなくていい｣外免切替や生保購入で､罪悪感なく崩壊する在日中国人のモラル | ライフ | 東洋経済オンライン",
                         "url":  "https://toyokeizai.net/articles/-/951888?utm_source=rss\u0026utm_medium=http\u0026utm_campaign=link_back",
                         "description":  "日本の試験や制度の不備に目をつけ､不正を行う中国人が増加する一方､母国の厳格な管理下で育った人々も日本の｢甘さ｣に驚いています。",
                         "publishedAt":  "2026-07-21T07:00:00+09:00",
                         "fetchedAt":  "2026-07-21T08:11:46+09:00"
                     },
                     {
                         "source":  "東洋経済オンライン",
                         "title":  "IHI財務部長｢2029年度以降は株主還元を拡大するフェーズ｣ 営業利益3000億円計画の勝算は？ | ビジネス | 東洋経済オンライン",
                         "url":  "https://toyokeizai.net/articles/-/951158?utm_source=rss\u0026utm_medium=http\u0026utm_campaign=link_back",
                         "description":  "IHIが2031年度までに営業利益を倍増し3,000億円を目指す成長戦略を打ち出しました。航空エンジンや防衛分野への大胆な投資､その裏に秘められた収益化のシナリオと課題とは。計画達成の勝算に迫ります。",
                         "publishedAt":  "2026-07-21T07:00:00+09:00",
                         "fetchedAt":  "2026-07-21T08:11:46+09:00"
                     },
                     {
                         "source":  "東洋経済オンライン",
                         "title":  "｢社会保険料を下げろ｣の大合唱が医療保障を壊す…病に苦しむ患者の負担増で現役世代の手取りを増やす危うさ | 政治・経済・投資 | 東洋経済オンライン",
                         "url":  "https://toyokeizai.net/articles/-/951571?utm_source=rss\u0026utm_medium=http\u0026utm_campaign=link_back",
                         "description":  "高市早苗政権が日本維新の会とともに掲げる｢現役世代の社会保険料負担の引き下げ｣。その一方で､医療や介護の現場では患者や利用者の負担増が進もうとしています。手取り増の美名のもと､社会保障の土台が細る危…",
                         "publishedAt":  "2026-07-21T06:40:00+09:00",
                         "fetchedAt":  "2026-07-21T08:11:46+09:00"
                     },
                     {
                         "source":  "東洋経済オンライン",
                         "title":  "｢こりゃ攻め落とせないわ｣｢まるで進撃の巨人！｣…ヨーロッパ人憧れの世界遺産だらけな《地中海の小国》が凄かった | ライフ | 東洋経済オンライン",
                         "url":  "https://toyokeizai.net/articles/-/951787?utm_source=rss\u0026utm_medium=http\u0026utm_campaign=link_back",
                         "description":  "古代の要塞都市の面影が色濃く残る､地中海に浮かぶある小国。城壁に守られた街の\"本物の異世界感\"と､ヨーロッパ屈指の\"リゾート地\"としての両面を､筆者が体感したリアルなエピソードと共に紹介します。",
                         "publishedAt":  "2026-07-21T06:30:00+09:00",
                         "fetchedAt":  "2026-07-21T08:11:46+09:00"
                     },
                     {
                         "source":  "東洋経済オンライン",
                         "title":  "中身はネジや手袋？顧客工場に無償で自販機を設置､ミスミグループ本社の｢売り切れしない自販機｣はこうして生まれた | ビジネス | 東洋経済オンライン",
                         "url":  "https://toyokeizai.net/articles/-/951762?utm_source=rss\u0026utm_medium=http\u0026utm_campaign=link_back",
                         "description":  "製造現場での間接材管理を一新するミスミの自動販売機｢フロー｣。欲しい資材を\"0日納期\"で手に入れられる仕組みは､どのようにして生まれ､進化したのでしょうか。現場の課題を解決した革新の舞台裏に迫ります。",
                         "publishedAt":  "2026-07-21T06:20:00+09:00",
                         "fetchedAt":  "2026-07-21T08:11:46+09:00"
                     },
                     {
                         "source":  "東洋経済オンライン",
                         "title":  "都内高級マンション､去る中国人と買う台湾人…中間富裕層は退潮も超富裕層は10億円超え物件を即決 | ビジネス | 東洋経済オンライン",
                         "url":  "https://toyokeizai.net/articles/-/951489?utm_source=rss\u0026utm_medium=http\u0026utm_campaign=link_back",
                         "description":  "中国人の中間富裕層が日本の不動産市場から軒並み姿を消しつつある一方で､超富裕層や台湾人投資家が活発な動きを見せています。ビザ厳格化や価格高騰という逆風下､それでもなぜ外国人の存在感が残り続けるのか。…",
                         "publishedAt":  "2026-07-21T06:15:00+09:00",
                         "fetchedAt":  "2026-07-21T08:11:46+09:00"
                     },
                     {
                         "source":  "東洋経済オンライン",
                         "title":  "完成物件は｢財産｣――住友不動産｢シティタワー千住大橋｣に見る値引きしない販売戦略の勝ちパターン | ビジネス | 東洋経済オンライン",
                         "url":  "https://toyokeizai.net/articles/-/951753?utm_source=rss\u0026utm_medium=http\u0026utm_campaign=link_back",
                         "description":  "千住大橋駅に2025年に完成した｢シティタワー千住大橋｣。住友不動産が誇るこのタワーマンションは､完成後のじっくり販売戦略で注目を集めています。",
                         "publishedAt":  "2026-07-21T06:10:00+09:00",
                         "fetchedAt":  "2026-07-21T08:11:46+09:00"
                     },
                     {
                         "source":  "東洋経済オンライン",
                         "title":  "三菱地所レジデンス､マンション事業粗利率37％の実力…番町･麹町など希少立地ばかりで存在感を発揮できる理由 | ビジネス | 東洋経済オンライン",
                         "url":  "https://toyokeizai.net/articles/-/951423?utm_source=rss\u0026utm_medium=http\u0026utm_campaign=link_back",
                         "description":  "千代田区･番町エリアで高級マンションを供給し続ける三菱地所レジデンス。その背景には､土地の歴史や文化と融合した唯一無二のものづくりと､地権者との信頼関係を生かした戦略があります。高利益率を維持する秘…",
                         "publishedAt":  "2026-07-21T06:05:00+09:00",
                         "fetchedAt":  "2026-07-21T08:11:46+09:00"
                     },
                     {
                         "source":  "東洋経済オンライン",
                         "title":  "中国の自動車輸出が初の月間100万台超…6月は前年比75％増､上期の国内販売4割減で海外市場に活路 | ビジネス | 東洋経済オンライン",
                         "url":  "https://toyokeizai.net/articles/-/951654?utm_source=rss\u0026utm_medium=http\u0026utm_campaign=link_back",
                         "description":  "中国自動車業界が驚異的な輸出攻勢をかけています。電気自動車（EV）やプラグインハイブリッド車（PHV）が海外需要を牽引し6月だけで初の100万台超えを記録しました。国内市場低迷のはけ口を求める動きは…",
                         "publishedAt":  "2026-07-21T06:00:00+09:00",
                         "fetchedAt":  "2026-07-21T08:11:46+09:00"
                     },
                     {
                         "source":  "東洋経済オンライン",
                         "title":  "爆騰が止まらない新築マンション｢値付け｣のからくり…進む｢立地｣と｢顧客｣の選別とデベロッパーの優勝劣敗 | ビジネス | 東洋経済オンライン",
                         "url":  "https://toyokeizai.net/articles/-/951273?utm_source=rss\u0026utm_medium=http\u0026utm_campaign=link_back",
                         "description":  "東京湾に突き出す中央区豊海町で､超高層マンション｢ザ 豊海タワー｣の誕生が注目を集めています。新築供給の減少と価格高騰が進む中､｢億ション｣も即完売する都市型住宅の今。その裏で高騰の連鎖と二極化が進…",
                         "publishedAt":  "2026-07-21T06:00:00+09:00",
                         "fetchedAt":  "2026-07-21T08:11:46+09:00"
                     },
                     {
                         "source":  "東洋経済オンライン",
                         "title":  "｢君はいつまで部活をやるつもりなのか！｣妻の両親に呼び出され…熱血教師は\"部活動の地域展開\"に何を思うか | キャリア・教育 | 東洋経済オンライン",
                         "url":  "https://toyokeizai.net/articles/-/948884?utm_source=rss\u0026utm_medium=http\u0026utm_campaign=link_back",
                         "description":  "生徒と共に全国大会を目指し､人生を賭けて部活指導に没頭した教員。その輝かしい成果の裏側には､家庭を犠牲にしたリアルな苦悩も潜んでいます。",
                         "publishedAt":  "2026-07-21T06:00:00+09:00",
                         "fetchedAt":  "2026-07-21T08:11:46+09:00"
                     },
                     {
                         "source":  "東洋経済オンライン",
                         "title":  "〈始まったカウントダウン〉小野薬品､｢オプジーボ後｣に挑む\"団体戦候補\"の顔ぶれ･･･一本足脱却で｢崖｣を回避なるか | ビジネス | 東洋経済オンライン",
                         "url":  "https://toyokeizai.net/articles/-/951723?utm_source=rss\u0026utm_medium=http\u0026utm_campaign=link_back",
                         "description":  "小野薬品工業のがん治療薬｢オプジーボ｣が特許切れのタイムリミットを間近に控え､同社の経営は大きな転機を迎えています。売上の過半を占める超大型薬の延命策と､後を託す新薬候補とは。特許切れ後を｢崖｣では…",
                         "publishedAt":  "2026-07-21T05:50:00+09:00",
                         "fetchedAt":  "2026-07-21T08:11:46+09:00"
                     },
                     {
                         "source":  "東洋経済オンライン",
                         "title":  "巨大化するAI半導体で業界が激震､レゾナック｢従来の開発では対応が難しい｣次世代パッケージ技術の標準化にどう挑む | ビジネス | 東洋経済オンライン",
                         "url":  "https://toyokeizai.net/articles/-/951907?utm_source=rss\u0026utm_medium=http\u0026utm_campaign=link_back",
                         "description":  "総合化学メーカーから半導体材料分野へ大転換を図るレゾナック･ホールディングス。生成AIブームとともに需要が急増する半導体材料で､世界のビッグテックと連携しながら勝ち筋を模索しています。半導体パッケー…",
                         "publishedAt":  "2026-07-21T05:40:00+09:00",
                         "fetchedAt":  "2026-07-21T08:11:46+09:00"
                     },
                     {
                         "source":  "東洋経済オンライン",
                         "title":  "26年内に新型SUVとして復活がアナウンスされて高まる期待…オフロード4WDの雄､三菱｢パジェロ｣の歴史を振り返る | ライフ | 東洋経済オンライン",
                         "url":  "https://toyokeizai.net/articles/-/951229?utm_source=rss\u0026utm_medium=http\u0026utm_campaign=link_back",
                         "description":  "三菱｢パジェロ｣が7年ぶりに復活し､新型SUVとして2026年に登場します。なぜ､パジェロが生まれ､人々の心をつかんだのか､その歴史を振り返ります。",
                         "publishedAt":  "2026-07-21T05:30:00+09:00",
                         "fetchedAt":  "2026-07-21T08:11:46+09:00"
                     },
                     {
                         "source":  "東洋経済オンライン",
                         "title":  "滋賀･近江鉄道｢上下分離｣で再生の兆し､官民連携強め地域振興､苦闘する地方ローカル線の先達となれるか | ビジネス | 東洋経済オンライン",
                         "url":  "https://toyokeizai.net/articles/-/951089?utm_source=rss\u0026utm_medium=http\u0026utm_campaign=link_back",
                         "description":  "少子高齢化に歯止めのかからない日本。全国各地で問題となっているのが、地方ローカル線の存廃だ。鉄道事業を営むには、車両や線路などの大規模な設備を用意せねばならず、安全のために定期的な保守と修繕も欠かせ…",
                         "publishedAt":  "2026-07-21T05:30:00+09:00",
                         "fetchedAt":  "2026-07-21T08:11:46+09:00"
                     },
                     {
                         "source":  "東洋経済オンライン",
                         "title":  "なぜアサヒはサイバー被害から｢最高益｣を狙えるのか…強気シナリオの裏にある株主還元の代償と迫る宿敵キリンの足音 | ビジネス | 東洋経済オンライン",
                         "url":  "https://toyokeizai.net/articles/-/951641?utm_source=rss\u0026utm_medium=http\u0026utm_campaign=link_back",
                         "description":  "本来であれば、2月中旬に行われるはずだった25年12月期の通期決算説明会は、5カ月遅れでようやく開かれた。7月8日、アサヒグループホールディングス（以下、アサヒGHD）は2025年12月期決算（国際…",
                         "publishedAt":  "2026-07-21T05:20:00+09:00",
                         "fetchedAt":  "2026-07-21T08:11:46+09:00"
                     },
                     {
                         "source":  "東洋経済オンライン",
                         "title":  "運転士｢ポロシャツ勤務OK｣変化する鉄道員のシンボル 小田急､相鉄に続き東京都交通局が制服に採用 | ビジネス | 東洋経済オンライン",
                         "url":  "https://toyokeizai.net/articles/-/951625?utm_source=rss\u0026utm_medium=http\u0026utm_campaign=link_back",
                         "description":  "鉄道員の代名詞ともいえる制服が､今大きく変わろうとしています。伝統的なイメージを守りつつも､熱中症対策や多様な働き方に対応しポロシャツなど新しい制服を導入する動きが拡大中。その背景や現場の反応とは？…",
                         "publishedAt":  "2026-07-21T04:30:00+09:00",
                         "fetchedAt":  "2026-07-21T08:11:46+09:00"
                     },
                     {
                         "source":  "東洋経済オンライン",
                         "title":  "【配当収入「年間800万円超」でFIRE達成】低年収\u0026株売買の才能ナシでもできた／「増配株」が今アツい理由／銘柄選び「3つのステップ」／\"自分に甘い”投資家だった／「高配当株」と「増配株」は違う | ビジネス | 東洋経済オンライン",
                         "url":  "https://toyokeizai.net/articles/-/952068?utm_source=rss\u0026utm_medium=http\u0026utm_campaign=link_back",
                         "description":  "元高校球児でフリーアナウンサーの上重聡がお送りする資産運用をテーマにした動画シリーズ。いつか「億り人」になれる日を目指して、資産運用の先輩からさまざまな極意を学んでいきます。今回のゲストは「増配株」…",
                         "publishedAt":  "2026-07-20T19:00:00+09:00",
                         "fetchedAt":  "2026-07-21T08:11:46+09:00"
                     },
                     {
                         "source":  "ダイヤモンド・オンライン",
                         "title":  "部下が「この上司はムリ」と思う瞬間・ナンバー1 - 3000件の職場の悩みを解決したプロが教える リーダーのふるまい大全",
                         "url":  "https://diamond.jp/articles/-/394791",
                         "description":  "部下から信頼される上司と、「この人とは一緒に働きたくない」と思われる上司。その違いは、特別なマネジメント手法ではなく、本人も気づかない日々のふるまいにあることが少なくない。では、部下が上司に見切りをつけるきっかけとは何なのだろうか。話題の書『リーダーのふるまい大全』の著者・本田淳也氏が、リーダーが陥りやすい落とし穴について解説する。",
                         "publishedAt":  "2026-07-21T07:10:00+09:00",
                         "fetchedAt":  "2026-07-21T08:11:48+09:00"
                     },
                     {
                         "source":  "ダイヤモンド・オンライン",
                         "title":  "「全く使えない社員」の口癖・ワースト1 - リーダーの仮面",
                         "url":  "https://diamond.jp/articles/-/393508",
                         "description":  "「部下に厳しく言ったら、ハラスメントになるかもしれない」。そんな不安から、必要な指導までためらってしまう管理職が増えています。しかし、本当にハラスメントになる上司は、「厳しい人」ではありません。むしろ、本人は良かれと思っているのに、知らないうちに部下を追い詰めてしまう人には、ある共通した特徴があるのです。この連載では、全ビジネスパーソンに必須の「リーダーシップ」のあり方について指南します。",
                         "publishedAt":  "2026-07-21T07:00:00+09:00",
                         "fetchedAt":  "2026-07-21T08:11:48+09:00"
                     },
                     {
                         "source":  "ダイヤモンド・オンライン",
                         "title":  "人前で話していると「頭が真っ白になってしまう」驚きの理由 - 言語化だけじゃ伝わんない",
                         "url":  "https://diamond.jp/articles/-/393535",
                         "description":  "「人前に立つと頭が真っ白になる」「言いたいことはあるのに言葉が出てこない」。そんな経験はありませんか。『言語化だけじゃ伝わんない』では、その原因は知識不足ではなく、「文章」という仕組みにあると語られています。本記事では、その意外な理由を紹介します。",
                         "publishedAt":  "2026-07-21T06:55:00+09:00",
                         "fetchedAt":  "2026-07-21T08:11:48+09:00"
                     },
                     {
                         "source":  "ダイヤモンド・オンライン",
                         "title":  "【一発アウト】部下が「この人には何も言わない」と決める上司の致命的フレーズ・ワースト1 - 伝え方ひとつで部下が動き出す 上司の「コミュ力」大全",
                         "url":  "https://diamond.jp/articles/-/393514",
                         "description":  "良かれと思ったそのアドバイス、実は部下へのプレッシャーになっていませんか？ 悩みを打ち明けた部下が求めているのは、スピーディーな正論ではなく、感情を受け止めてもらう「安心感」です。上司が陥りがちな「共感しているつもり」の罠に気づき、相手が受け取りやすい言葉を投げ返す「会話のキャッチボール」の極意とは？部下との信頼を深める対話術を紹介します。",
                         "publishedAt":  "2026-07-21T06:50:00+09:00",
                         "fetchedAt":  "2026-07-21T08:11:48+09:00"
                     },
                     {
                         "source":  "ダイヤモンド・オンライン",
                         "title":  "部下を困らせる「上司の声掛け」・ワースト1 - 会社から期待されている人の習慣115",
                         "url":  "https://diamond.jp/articles/-/394915",
                         "description":  "部下にフランクに声をかけ、本音を引き出そうと努めている上司は多い。しかし、その何気ない一言こそが、部下のやる気を奪い、心を閉ざす原因になっているかもしれない。17万人の行動データが解き明かす、部下に嫌われる上司が連発している「最悪の言葉」とは？",
                         "publishedAt":  "2026-07-21T06:45:00+09:00",
                         "fetchedAt":  "2026-07-21T08:11:48+09:00"
                     },
                     {
                         "source":  "ダイヤモンド・オンライン",
                         "title":  "「引退後に後悔する人」の特徴・ワースト1 - 糖毒脳",
                         "url":  "https://diamond.jp/articles/-/394990",
                         "description":  "仕事を引退したら、旅行に行きたい。好きなことをしたい。そのために、お金を貯めている。そういう人は多いかもしれない。しかし、引退後の生活を楽しむためには、もっと大切なものがある。元オックスフォード大の医学研究者で、「糖と脳」の専門家として知られる医師・下村健寿氏が伝える、「将来後悔しないために今すぐできること」を紹介する。",
                         "publishedAt":  "2026-07-21T06:40:00+09:00",
                         "fetchedAt":  "2026-07-21T08:11:48+09:00"
                     },
                     {
                         "source":  "ダイヤモンド・オンライン",
                         "title":  "【勉強法】親の「お説教」になってない？ 子どもの成績を伸ばす親子の「黄金比率」 - 成績アップは「国語」で決まる！ 偏差値45からの東大合格「完全独学★勉強法」",
                         "url":  "https://diamond.jp/articles/-/391191",
                         "description":  "良かれと思った熱心な解説が、気づけば親の「お説教」にすり替わっていませんか？ 親が熱弁を振るい、子どもが黙り込んでしまう対話は逆効果です。子どもの思考力を伸ばすカギは、親子の発言量を「1：1」にする黄金比率にあります。親が目指すべきは熱血講師ではなく、笑顔で言葉を引き出す名司会者。子どもが安心して自分の言葉で話し出す、東大式・最高の伴走術を紹介します。",
                         "publishedAt":  "2026-07-21T06:35:00+09:00",
                         "fetchedAt":  "2026-07-21T08:11:48+09:00"
                     },
                     {
                         "source":  "ダイヤモンド・オンライン",
                         "title":  "仕事ができない人は「何かできることはある？」と言う。できる人はどう言う？ - 仕事ができる上司の当たり前",
                         "url":  "https://diamond.jp/articles/-/394993",
                         "description":  "部下の進捗が思わしくないとき、「何か困っていることはある？」と声をかけるだけで終わってしまっていないだろうか。上司に求められる関与は、もう一歩先にある。",
                         "publishedAt":  "2026-07-21T06:25:00+09:00",
                         "fetchedAt":  "2026-07-21T08:11:48+09:00"
                     },
                     {
                         "source":  "ダイヤモンド・オンライン",
                         "title":  "優秀な人ほど「やる気がなくなる」組織の共通点・ワースト1 - やり抜く力",
                         "url":  "https://diamond.jp/articles/-/392386",
                         "description":  "IQや才能など、生まれつき備わった能力よりも、「やり抜く力」こそが成功のカギだ――。そうした研究成果をまとめた書籍が、発売から10年経った今でも話題だ。本連載では、坂井風太氏にビジネスパーソンに必要な「やり抜く力（グリット）」についてインタビューした内容を全4回でお届けする。 第3回では、グリットの欠如が組織に与える負の連鎖、そして「諦め癖」が染みついた組織が陥りがちな問題について聞いた。",
                         "publishedAt":  "2026-07-21T06:05:00+09:00",
                         "fetchedAt":  "2026-07-21T08:11:48+09:00"
                     },
                     {
                         "source":  "ダイヤモンド・オンライン",
                         "title":  "医師が後悔するキケンな飲み物「よかれと思って毎日のように…」→肝臓に一番悪い習慣だった！〈再配信〉 - ニュースな本",
                         "url":  "https://diamond.jp/articles/-/394622",
                         "description":  "私たちは知らず知らずのうちに、肝臓に危険な「果糖ブドウ糖液糖」を摂っている。「皮をむいたオレンジはOKだけど市販のスムージーはNG」だと話す著者が、果糖の適切な摂取方法について解説する。本稿は、尾形哲『甘い飲み物が肝臓を殺す』（幻冬舎新書）の一部を抜粋・編集したものです。",
                         "publishedAt":  "2026-07-21T06:00:00+09:00",
                         "fetchedAt":  "2026-07-21T08:11:48+09:00"
                     },
                     {
                         "source":  "ダイヤモンド・オンライン",
                         "title":  "「日本の高学歴」が「フィンランドの低学歴」になる残念な理由〈再配信〉 - ニュースな本",
                         "url":  "https://diamond.jp/articles/-/394181",
                         "description":  "子どもの将来のため、教育に頭を悩ませている親や教育者は少なくありません。フィンランドと日本、両方で子育てを経験した岩竹美加子氏は「フィンランドの教育は質が高くてシンプルだ」と話します。岩竹さんの著書『フィンランドの高校生が学んでいる人生を変える教養』（青春出版社）から、その教育の特徴、そしてフィンランド独自の授業『人生観の知識』について、抜粋して紹介します。",
                         "publishedAt":  "2026-07-21T06:00:00+09:00",
                         "fetchedAt":  "2026-07-21T08:11:48+09:00"
                     },
                     {
                         "source":  "ダイヤモンド・オンライン",
                         "title":  "【心が軽くなる】松井玲奈が語る、人生を好転させるために必要な“すごい習慣” - 世界の果てのカフェ",
                         "url":  "https://diamond.jp/articles/-/393822",
                         "description":  "全世界45言語に翻訳され、累計600万部を突破したことで大きな話題を呼んでいる書籍がある。俳優や作家として活動する松井玲奈さんは、その本に描かれたエピソードに触れ、「自分の思いを言葉にし、他者と向き合うことが人生や仕事を前に進める力になる」と語る。 本連載では、松井さんに、表現者としての現在地、そして迷いながらも進み続ける原動力についてインタビューした内容を全4回でお届けする。最終回では、俳優としての葛藤を乗り越えるために大切にしている「人と人との対話」について話を聞いた。",
                         "publishedAt":  "2026-07-21T06:00:00+09:00",
                         "fetchedAt":  "2026-07-21T08:11:48+09:00"
                     },
                     {
                         "source":  "ダイヤモンド・オンライン",
                         "title":  "アクセンチュアの50代前半・マネージャー級の年収は？【5000件の口コミ情報データ】 - ダイヤモンド・口コミ情報",
                         "url":  "https://diamond.jp/articles/-/394655",
                         "description":  "ダイヤモンド・口コミ情報では、年収・給与制度に関するアンケートを実施、寄せられた回答をもとに年収データを公開しています。今回は「アクセンチュアの50代前半・マネージャー級」です。",
                         "publishedAt":  "2026-07-21T05:30:00+09:00",
                         "fetchedAt":  "2026-07-21T08:11:49+09:00"
                     },
                     {
                         "source":  "ダイヤモンド・オンライン",
                         "title":  "日本IBMの50代後半・部長級の年収は？【5000件の口コミ情報データ】 - ダイヤモンド・口コミ情報",
                         "url":  "https://diamond.jp/articles/-/395110",
                         "description":  "ダイヤモンド・口コミ情報では、年収・給与制度に関するアンケートを実施、寄せられた回答をもとに年収データを公開しています。今回は「日本IBMの50代後半・部長級」です。",
                         "publishedAt":  "2026-07-21T05:25:00+09:00",
                         "fetchedAt":  "2026-07-21T08:11:49+09:00"
                     },
                     {
                         "source":  "ダイヤモンド・オンライン",
                         "title":  "イケアのビンテージ品、今や高価な収集品に - WSJ PickUp",
                         "url":  "https://diamond.jp/articles/-/395072",
                         "description":  "イケアは、一般大衆に優れたデザインの家具を手頃な価格で届けるという理念に基づきブランドを確立した。ところが今、ビンテージ品は手の届かないことが少なくない。",
                         "publishedAt":  "2026-07-21T05:05:00+09:00",
                         "fetchedAt":  "2026-07-21T08:11:49+09:00"
                     },
                     {
                         "source":  "ダイヤモンド・オンライン",
                         "title":  "【オピニオン】中国経済、状態は見掛けより悪い - WSJ PickUp",
                         "url":  "https://diamond.jp/articles/-/395071",
                         "description":  "中国で物事が計画通りに進んでいると共産党でさえ主張できない場合、同国経済に何らかの異変が起きていることが分かる。",
                         "publishedAt":  "2026-07-21T05:00:00+09:00",
                         "fetchedAt":  "2026-07-21T08:11:49+09:00"
                     },
                     {
                         "source":  "ダイヤモンド・オンライン",
                         "title":  "転倒検知や血圧管理だけではない…高齢者向けスマートウォッチ選び、最大の盲点とは - ニュース3面鏡",
                         "url":  "https://diamond.jp/articles/-/394896",
                         "description":  "高齢の親の見守り手段として注目されるスマートウォッチ。転倒検知や健康管理機能だけでなく、導入時に見落とされがちなポイントや、親のスマートフォン環境に合わせた選び方を専門家が解説する。",
                         "publishedAt":  "2026-07-21T05:00:00+09:00",
                         "fetchedAt":  "2026-07-21T08:11:49+09:00"
                     },
                     {
                         "source":  "ダイヤモンド・オンライン",
                         "title":  "顔のくま取りや肌質改善を謳う「bFGF注射」に製薬会社が注意喚起、訴訟相次ぐ…それでも大手美容クリニックが施術を止めない本当の理由 - 狂乱の美容医療 ～膨張市場の「闇」と錬金術",
                         "url":  "https://diamond.jp/articles/-/395043",
                         "description":  "顔のくま取りや肌質改善をうたい大手美容クリニックで提供されている「bFGF注射」を巡り、美容クリニックを相手取った訴訟が相次いでいる。注入後に細胞が必要以上に増殖し、不自然な皮膚隆起やしこりが残る深刻な副作用が多発しているからだ。使用されている薬剤の製造元・科研製薬も、10年以上前から「皮下注入は対象外」と異例の注意喚起を続けてきた。それにもかかわらず、なぜ大手は施術をやめないのか。独自入手した当時の「同意書」の中身などから、美容医療界のモラルハザードの深層に迫る。",
                         "publishedAt":  "2026-07-21T04:55:00+09:00",
                         "fetchedAt":  "2026-07-21T08:11:49+09:00"
                     },
                     {
                         "source":  "ダイヤモンド・オンライン",
                         "title":  "三菱自動車「過去約10年の役員人事」に見る大株主勢力図の激変、日産と三菱グループ3社で存在感を増した勢力・薄れた勢力は？ - 自動車 解体",
                         "url":  "https://diamond.jp/articles/-/394959",
                         "description":  "三菱自動車は、日産自動車と三菱グループ御三家という主要株主4社に支えられてきた。4社は株式を保有するだけでなく、役員を送り込み、経営にも深く関わってきた。では、約10年で、その布陣はどう変わったのか。ダイヤモンド編集部は約10年分の役員人事を分析した。役員人事から三菱自を巡るグループ力学の変化を読み解く。",
                         "publishedAt":  "2026-07-21T04:50:00+09:00",
                         "fetchedAt":  "2026-07-21T08:11:49+09:00"
                     },
                     {
                         "source":  "ダイヤモンド・オンライン",
                         "title":  "総合商社の給料ランキング【主要7社】伊藤忠が大幅増！「年収2100万円」突破でトップに立ったのはどこ？ - 26年 給料ランキング",
                         "url":  "https://diamond.jp/articles/-/395004",
                         "description":  "高年収で就活生からも人気が高い総合商社。近年は業績絶好調で、給与も爆発的に増加している。しかし、一口に総合商社といっても、その特徴は各社で異なる。中でも生活消費ビジネスに強みを持つ伊藤忠商事は、資源ビジネスを得意とする財閥系の三菱商事や三井物産に対抗心を燃やし、業績面で猛追してきた。では、給与面ではどのような序列になっているのだろうか。七大商社（伊藤忠商事、三井物産、三菱商事、住友商事、丸紅、豊田通商、双日）の2025年度の給与ランキングを公開する。",
                         "publishedAt":  "2026-07-21T04:45:00+09:00",
                         "fetchedAt":  "2026-07-21T08:11:49+09:00"
                     },
                     {
                         "source":  "ダイヤモンド・オンライン",
                         "title":  "住宅メーカーの給料ランキング【主要8社】5位積水ハウス、2位住友林業、1位は？業績悪化の中堅メーカーは大幅ダウン、絶対王者の大和ハウス工業は大台突破なるか？ - 26年 給料ランキング",
                         "url":  "https://diamond.jp/articles/-/395058",
                         "description":  "国内の人口減少に加え、中東情勢の緊迫化に伴う資材高騰のダブルパンチで経営環境の悪化に拍車がかかる住宅業界。海外事業へのシフトや、リフォーム事業といった非住宅分野の強化など、生き残りを懸けた各社の戦略が多様化する中、社員の待遇にはどのような格差が生じているのだろうか。主要8社の最新の給料ランキングを一挙紹介する。",
                         "publishedAt":  "2026-07-21T04:40:00+09:00",
                         "fetchedAt":  "2026-07-21T08:11:49+09:00"
                     },
                     {
                         "source":  "ダイヤモンド・オンライン",
                         "title":  "社外取より社員の方がリッチ!?「従業員vs社外取締役」報酬逆転ランキング【大企業41社202人】キーエンス、光通信、フジ・メディアHD… - 社外取10821人の全序列【2026最新版】熱狂バブルの落とし穴",
                         "url":  "https://diamond.jp/articles/-/395009",
                         "description":  "高額報酬のイメージが強い社外取締役だが、実は「社員の平均年収」の方が社外取の推計報酬額を上回る大企業も少なくない。ダイヤモンド編集部は、時価総額3000億円以上、かつ従業員の平均年収1000万円以上の上場企業を対象に、社外取の推計報酬額が従業員の平均年収と比べてどれほどの水準かを独自試算した。「従業員vs社外取」の報酬逆転ランキングには時価総額18兆円超のキーエンスや、平均年収2400万円超の光通信も登場する。",
                         "publishedAt":  "2026-07-21T04:35:00+09:00",
                         "fetchedAt":  "2026-07-21T08:11:49+09:00"
                     },
                     {
                         "source":  "ダイヤモンド・オンライン",
                         "title":  "【東京】JA“赤字＆消滅”危険度ランキング！4農協が赤字に転落する損益シミュレーションを公開！国債の暴落ショックに耐えられないJAを独自試算で解明 - 儲かる農業 JA・豪農・アグリビジネス大激変",
                         "url":  "https://diamond.jp/articles/-/391697",
                         "description":  "東京都の農協の経営が危機にひんしている。金利の上昇によって価格が下落した国債の“損切り”を迫られて赤字に転落した他県の農協の後を追うように、経営の悪化が見込まれているのだ。東京都において、債券の暴落ショックに耐えられない可能性が高い農協を、独自試算であぶり出した。試算の結果、都内の15JA中4JAが赤字に転落することが分かった。",
                         "publishedAt":  "2026-07-21T04:30:00+09:00",
                         "fetchedAt":  "2026-07-21T08:11:49+09:00"
                     },
                     {
                         "source":  "ダイヤモンド・オンライン",
                         "title":  "OpenAI、SpaceX…話題の大型IPOに飛びつくな！米著名投資家が解説「大半が期待外れ」に終わる理由 - Diamond マーケットラボ",
                         "url":  "https://diamond.jp/articles/-/394968",
                         "description":  "日本の新規株式公開（IPO）市場が低迷する一方、米国ではSpaceXに続き、OpenAIやAnthropicなどの大型上場観測が投資家を熱狂させている。だが、米著名投資家ケン・フィッシャー氏は、大半のIPO株は歴史的に市場平均を下回り、上場直後の急騰も長続きしないと警告する。なぜ創業者とIPO株を買う投資家の間には、埋めがたい情報格差があるのか。日米の事例と長期データから、IPOの成功体験が過信や集中投資を招き、市場全体の過熱サインにもなる理由を読み解く。",
                         "publishedAt":  "2026-07-21T04:25:00+09:00",
                         "fetchedAt":  "2026-07-21T08:11:49+09:00"
                     },
                     {
                         "source":  "ダイヤモンド・オンライン",
                         "title":  "「危機管理・成長投資」の財源は“つなぎ国債”に!?骨太原案で見えた高市積極財政の期待とリスク - 高市内閣2.0 どうなる？経済・市場・政策",
                         "url":  "https://diamond.jp/articles/-/394969",
                         "description":  "高市政権の財政運営や来年度予算方針を示す「骨太2026」の原案は、政府債務残高対GDP比を柱にした財政目標や「強く豊かな日本」投資枠の創設など、「成長重視」を前面に出した。補正予算依存脱却などの取り組みは評価できる一方、新投資枠の財源はつなぎ国債としている点や財政運営の前提となる成長率見通しを高めに見積もるなど、歳出が膨らむ懸念はなお残る。",
                         "publishedAt":  "2026-07-21T04:20:00+09:00",
                         "fetchedAt":  "2026-07-21T08:11:49+09:00"
                     }
                 ]
}
